voai_client/__init__.py
voai_client/cli.py
voai_client-0.2.0.dist-info/METADATA
voai_client-0.2.0.dist-info/WHEEL
voai_client-0.2.0.dist-info/entry_points.txt
voai_client-0.2.0.dist-info/top_level.txt
voai_client-0.2.0.dist-info/RECORD
