Metadata-Version: 2.4
Name: voai-client
Version: 0.2.0
Summary: Python SDK for voai.ai VoiceAPI (TTS / generate-voice / generate-dialogue)
Author-email: Your Name <you@example.com>
Project-URL: Homepage, https://github.com/yourname/voai-client
Classifier: Programming Language :: Python :: 3
Classifier: License :: OSI Approved :: MIT License
Classifier: Operating System :: OS Independent
Requires-Python: >=3.8
Requires-Dist: requests>=2.31
Provides-Extra: dev
Requires-Dist: pytest>=8.0; extra == "dev"
Requires-Dist: requests-mock>=1.11; extra == "dev"
